brick_model_summarizer/__init__.py
brick_model_summarizer/ahu_info.py
brick_model_summarizer/analyzer.py
brick_model_summarizer/building_info.py
brick_model_summarizer/central_plant_info.py
brick_model_summarizer/class_tag_checker.py
brick_model_summarizer/meters_info.py
brick_model_summarizer/timeseries_references.py
brick_model_summarizer/utils.py
brick_model_summarizer/zone_info.py
brick_model_summarizer-0.4.1.dist-info/LICENSE
brick_model_summarizer-0.4.1.dist-info/METADATA
brick_model_summarizer-0.4.1.dist-info/WHEEL
brick_model_summarizer-0.4.1.dist-info/top_level.txt
brick_model_summarizer-0.4.1.dist-info/RECORD
