Metadata-Version: 2.2
Name: brick_model_summarizer
Version: 0.4.1
Summary: A package for summarizing BRICK models
Home-page: https://github.com/bbartling/BrickModelSummarizer
Author: Ben Bartling
Author-email: ben.bartling@gmail.com
Classifier: Programming Language :: Python :: 3
Classifier: License :: OSI Approved :: MIT License
Classifier: Operating System :: OS Independent
Requires-Python: >=3.6
License-File: LICENSE
Requires-Dist: black
Requires-Dist: rdflib
Requires-Dist: pytest
Dynamic: author
Dynamic: author-email
Dynamic: classifier
Dynamic: description
Dynamic: description-content-type
Dynamic: home-page
Dynamic: requires-dist
Dynamic: requires-python
Dynamic: summary
